<!--
 Copyright (c) 2014 Juniper Networks, Inc. All rights reserved.
 -->
<urlLists>
    <require>
        <define>parseURLReq</define>
        <path>process.mainModule.exports["corePath"] + '/src/serverroot/common/parseURLRequire'</path>
    </require>
    <require>
        <define>routesHandler</define>
        <path>process.mainModule.exports["corePath"] + '/src/serverroot/web/routes/handler'</path>
    </require>
    <require>
        <define>virtualroutersconfigapi</define>
        <path>./virtualroutersconfig.api</path>
    </require>
    <!-- API / Feature definition for quotas configuration -->
    <!-- 1. fetch virtual routers - /api/tenants/config/virtual-routers/,
                                                 getVirtualRouters
    --> 
    <item>
        <url>/api/tenants/config/virtual-routers-list</url>
        <method>get</method>
        <feature>virtualroutersconfig</feature>
        <callback>virtualroutersconfigapi.getVirtualRoutersList</callback>
    </item>
    <item>
        <url>/api/tenants/config/virtual-routers</url>
        <method>get</method>
        <feature>virtualroutersconfig</feature>
        <callback>virtualroutersconfigapi.getVirtualRouters</callback>
    </item>
    <item>
        <url>/api/tenants/config/virtual-routers-detail</url>
        <method>get</method>
        <feature>virtualroutersconfig</feature>
        <callback>virtualroutersconfigapi.getVirtualRoutersWithDetail</callback>
    </item>
    <item>
        <url>/api/tenants/config/virtual-routers</url>
        <method>post</method>
        <feature>virtualroutersconfig</feature>
        <callback>virtualroutersconfigapi.createVirtualRouters</callback>
    </item>   
    <item>    
        <url>/api/tenants/config/virtual-router/:id</url>
        <method>put</method>
        <feature>virtualroutersconfig</feature>
        <callback>virtualroutersconfigapi.updateVirtualRouters</callback>
    </item>    
    <item>    
        <url>/api/tenants/config/virtual-router/:id</url>
        <method>delete</method>
        <feature>virtualroutersconfig</feature>
        <callback>virtualroutersconfigapi.deleteVirtualRouters</callback>
    </item>
</urlLists>

